[{"_path":"/bb/fuck","_dir":"bb","_draft":false,"_partial":false,"_locale":"","_empty":false,"title":"烦死了","description":"真的好烦，不知道为啥，感觉好累，感觉一直不被人认可，莫名卷入了精神内耗，操！","_type":"markdown","_id":"content:bb:fuck.md","_source":"content","_file":"bb/fuck.md","_extension":"md"},{"_path":"/modernwarships","_dir":"","_draft":false,"_partial":false,"_locale":"","_empty":false,"title":"前言","description":"此处将作为六月份后现代战舰视频装备评测等视频的文字版本发布地，敬请期待","_type":"markdown","_id":"content:modernwarships:index.md","_source":"content","_file":"modernwarships/index.md","_extension":"md"}]